setup.py
review_together/__init__.py
review_together/admin_urls.py
review_together/extension.py
review_together/forms.py
review_together.egg-info/PKG-INFO
review_together.egg-info/SOURCES.txt
review_together.egg-info/dependency_links.txt
review_together.egg-info/entry_points.txt
review_together.egg-info/not-zip-safe
review_together.egg-info/top_level.txt