Metadata-Version: 1.0
Name: review-together
Version: 1.0.0b
Summary: Add chat functionality to Review Board
Home-page: UNKNOWN
Author: Mike Conley
Author-email: UNKNOWN
License: UNKNOWN
Platform: UNKNOWN
